Workbook

Sheet Raw Data
A1: Transaction_ID | B1: Year | C1: Quarter | D1: Product | E1: Revenue | F1: Cost | G1: Profit
A2: TXN-1000 | B2: 2023 | C2: Q1 | D2: Widget Pro | E2: 15819 | F2: 9196.41 | G2: 6622.59
A3: TXN-1001 | B3: 2023 | C3: Q1 | D3: Widget Pro | E3: 23024 | F3: 15294.53 | G3: 7729.47
A4: TXN-1002 | B4: 2023 | C4: Q1 | D4: Widget Pro | E4: 39132 | F4: 26750.67 | G4: 12381.33
A5: TXN-1003 | B5: 2023 | C5: Q1 | D5: Widget Pro | E5: 39270 | F5: 21883.26 | G5: 17386.74
A6: TXN-1004 | B6: 2023 | C6: Q1 | D6: Widget Standard | E6: 21825 | F6: 16940.26 | G6: 4884.74
A7: TXN-1005 | B7: 2023 | C7: Q1 | D7: Widget Standard | E7: 11070 | F7: 8344.16 | G7: 2725.84
A8: TXN-1006 | B8: 2023 | C8: Q1 | D8: Widget Standard | E8: 24559 | F8: 17381.82 | G8: 7177.18
A9: TXN-1007 | B9: 2023 | C9: Q1 | D9: Widget Standard | E9: 14515 | F9: 10074.54 | G9: 4440.46
A10: TXN-1008 | B10: 2023 | C10: Q1 | D10: Service Package | E10: 11873 | F10: 7193.99 | G10: 4679.01
A11: TXN-1009 | B11: 2023 | C11: Q1 | D11: Service Package | E11: 14654 | F11: 8709.78 | G11: 5944.22
A12: TXN-1010 | B12: 2023 | C12: Q1 | D12: Service Package | E12: 19242 | F12: 12482.29 | G12: 6759.71
A13: TXN-1011 | B13: 2023 | C13: Q1 | D13: Service Package | E13: 18202 | F13: 11250.08 | G13: 6951.92
... A187: TXN-1185 | B187: 2024 | C187: Q4 | D187: Accessory Kit | E187: 3864 | F187: 3198.26 | G187: 665.74

Sheet Dashboard
A1: Executive Sales Performance Dashboard
A3: Instructions: Complete the analysis below using the Raw Data tab. All calculations should use formulas.
A5: Quarterly Performance Summary
A7: Product | B7: Quarter | C7: Total Revenue | D7: Weighted Avg Margin | E7: Rolling 3-Mo Trend | F7: YoY Margin Delta | G7: Margin Health
A8: Widget Pro | B8: 2023 Q1 | C8: =SUMIFS('Raw Data'!$E$2:$E$187,'Raw Data'!$D$2:$D$187,$A8,'Raw Data'!$B$2:$B$187,VALUE(LEFT($B8,4)),'Raw Data'!$C$2:$C$187,RIGHT($B8,2)) -> 117245 | D8: {=SUMPRODUCT(('Raw Data'!$D$2:$D$187=$A8)*('Raw Data'!$B$2:$B$187=(LEFT($B8,4)))*('Raw Data'!$C$2:$C$187=RIGHT($B8,2))*'Raw Data'!$G$2:$G$187)/C8} -> 0.37630713 | E8: =IF(AND(LEFT($B8,4)="2023",RIGHT($B8,2)="Q1"),"N/A",D8-D7) -> N/A | F8: {=IF(LEFT($B8,4)="2023","N/A",D8-INDEX($D$8:$D$39,MATCH($A8&LEFT($B8,4)-1&RIGHT($B8,2),$A$8:$A$39&LEFT($B$8:$B$39,4)&RIGHT($B$8:$B$39,2),0)))} -> N/A | G8: =IF(D8>0.35,"Strong",IF(D8>=0.2,"Moderate","At Risk")) -> Strong
A9: Widget Pro | B9: 2023 Q2 | C9: =SUMIFS('Raw Data'!$E$2:$E$187,'Raw Data'!$D$2:$D$187,$A9,'Raw Data'!$B$2:$B$187,VALUE(LEFT($B9,4)),'Raw Data'!$C$2:$C$187,RIGHT($B9,2)) -> 158778 | D9: {=SUMPRODUCT(('Raw Data'!$D$2:$D$187=$A9)*('Raw Data'!$B$2:$B$187=(LEFT($B9,4)))*('Raw Data'!$C$2:$C$187=RIGHT($B9,2))*'Raw Data'!$G$2:$G$187)/C9} -> 0.35548514 | E9: =IF(AND(LEFT($B9,4)="2023",RIGHT($B9,2)="Q1"),"N/A",D9-D8) -> -0.020821992 | F9: {=IF(LEFT($B9,4)="2023","N/A",D9-INDEX($D$8:$D$39,MATCH($A9&LEFT($B9,4)-1&RIGHT($B9,2),$A$8:$A$39&LEFT($B$8:$B$39,4)&RIGHT($B$8:$B$39,2),0)))} -> N/A | G9: =IF(D9>0.35,"Strong",IF(D9>=0.2,"Moderate","At Risk")) -> Strong
A10: Widget Pro | B10: 2023 Q3 | C10: =SUMIFS('Raw Data'!$E$2:$E$187,'Raw Data'!$D$2:$D$187,$A10,'Raw Data'!$B$2:$B$187,VALUE(LEFT($B10,4)),'Raw Data'!$C$2:$C$187,RIGHT($B10,2)) -> 139128 | D10: {=SUMPRODUCT(('Raw Data'!$D$2:$D$187=$A10)*('Raw Data'!$B$2:$B$187=(LEFT($B10,4)))*('Raw Data'!$C$2:$C$187=RIGHT($B10,2))*'Raw Data'!$G$2:$G$187)/C10} -> 0.36162634 | E10: =IF(AND(LEFT($B10,4)="2023",RIGHT($B10,2)="Q1"),"N/A",D10-D9) -> 0.0061412013 | F10: {=IF(LEFT($B10,4)="2023","N/A",D10-INDEX($D$8:$D$39,MATCH($A10&LEFT($B10,4)-1&RIGHT($B10,2),$A$8:$A$39&LEFT($B$8:$B$39,4)&RIGHT($B$8:$B$39,2),0)))} -> N/A | G10: =IF(D10>0.35,"Strong",IF(D10>=0.2,"Moderate","At Risk")) -> Strong
A11: Widget Pro | B11: 2023 Q4 | C11: =SUMIFS('Raw Data'!$E$2:$E$187,'Raw Data'!$D$2:$D$187,$A11,'Raw Data'!$B$2:$B$187,VALUE(LEFT($B11,4)),'Raw Data'!$C$2:$C$187,RIGHT($B11,2)) -> 195263 | D11: {=SUMPRODUCT(('Raw Data'!$D$2:$D$187=$A11)*('Raw Data'!$B$2:$B$187=(LEFT($B11,4)))*('Raw Data'!$C$2:$C$187=RIGHT($B11,2))*'Raw Data'!$G$2:$G$187)/C11} -> 0.38824432 | E11: =IF(AND(LEFT($B11,4)="2023",RIGHT($B11,2)="Q1"),"N/A",D11-D10) -> 0.026617973 | F11: {=IF(LEFT($B11,4)="2023","N/A",D11-INDEX($D$8:$D$39,MATCH($A11&LEFT($B11,4)-1&RIGHT($B11,2),$A$8:$A$39&LEFT($B$8:$B$39,4)&RIGHT($B$8:$B$39,2),0)))} -> N/A | G11: =IF(D11>0.35,"Strong",IF(D11>=0.2,"Moderate","At Risk")) -> Strong
A12: Widget Pro | B12: 2024 Q1 | C12: =SUMIFS('Raw Data'!$E$2:$E$187,'Raw Data'!$D$2:$D$187,$A12,'Raw Data'!$B$2:$B$187,VALUE(LEFT($B12,4)),'Raw Data'!$C$2:$C$187,RIGHT($B12,2)) -> 230966 | D12: {=SUMPRODUCT(('Raw Data'!$D$2:$D$187=$A12)*('Raw Data'!$B$2:$B$187=(LEFT($B12,4)))*('Raw Data'!$C$2:$C$187=RIGHT($B12,2))*'Raw Data'!$G$2:$G$187)/C12} -> 0.39270096 | E12: =IF(AND(LEFT($B12,4)="2023",RIGHT($B12,2)="Q1"),"N/A",D12-D11) -> 0.0044566437 | F12: {=IF(LEFT($B12,4)="2023","N/A",D12-INDEX($D$8:$D$39,MATCH($A12&LEFT($B12,4)-1&RIGHT($B12,2),$A$8:$A$39&LEFT($B$8:$B$39,4)&RIGHT($B$8:$B$39,2),0)))} -> 0.016393826 | G12: =IF(D12>0.35,"Strong",IF(D12>=0.2,"Moderate","At Risk")) -> Strong
A13: Widget Pro | B13: 2024 Q2 | C13: =SUMIFS('Raw Data'!$E$2:$E$187,'Raw Data'!$D$2:$D$187,$A13,'Raw Data'!$B$2:$B$187,VALUE(LEFT($B13,4)),'Raw Data'!$C$2:$C$187,RIGHT($B13,2)) -> 142170 | D13: {=SUMPRODUCT(('Raw Data'!$D$2:$D$187=$A13)*('Raw Data'!$B$2:$B$187=(LEFT($B13,4)))*('Raw Data'!$C$2:$C$187=RIGHT($B13,2))*'Raw Data'!$G$2:$G$187)/C13} -> 0.41061813 | E13: =IF(AND(LEFT($B13,4)="2023",RIGHT($B13,2)="Q1"),"N/A",D13-D12) -> 0.017917173 | F13: {=IF(LEFT($B13,4)="2023","N/A",D13-INDEX($D$8:$D$39,MATCH($A13&LEFT($B13,4)-1&RIGHT($B13,2),$A$8:$A$39&LEFT($B$8:$B$39,4)&RIGHT($B$8:$B$39,2),0)))} -> 0.05513299 | G13: =IF(D13>0.35,"Strong",IF(D13>=0.2,"Moderate","At Risk")) -> Strong
A14: Widget Pro | B14: 2024 Q3 | C14: =SUMIFS('Raw Data'!$E$2:$E$187,'Raw Data'!$D$2:$D$187,$A14,'Raw Data'!$B$2:$B$187,VALUE(LEFT($B14,4)),'Raw Data'!$C$2:$C$187,RIGHT($B14,2)) -> 196327 | D14: {=SUMPRODUCT(('Raw Data'!$D$2:$D$187=$A14)*('Raw Data'!$B$2:$B$187=(LEFT($B14,4)))*('Raw Data'!$C$2:$C$187=RIGHT($B14,2))*'Raw Data'!$G$2:$G$187)/C14} -> 0.40558334 | E14: =IF(AND(LEFT($B14,4)="2023",RIGHT($B14,2)="Q1"),"N/A",D14-D13) -> -0.0050347952 | F14: {=IF(LEFT($B14,4)="2023","N/A",D14-INDEX($D$8:$D$39,MATCH($A14&LEFT($B14,4)-1&RIGHT($B14,2),$A$8:$A$39&LEFT($B$8:$B$39,4)&RIGHT($B$8:$B$39,2),0)))} -> 0.043956994 | G14: =IF(D14>0.35,"Strong",IF(D14>=0.2,"Moderate","At Risk")) -> Strong
A15: Widget Pro | B15: 2024 Q4 | C15: =SUMIFS('Raw Data'!$E$2:$E$187,'Raw Data'!$D$2:$D$187,$A15,'Raw Data'!$B$2:$B$187,VALUE(LEFT($B15,4)),'Raw Data'!$C$2:$C$187,RIGHT($B15,2)) -> 156548 | D15: {=SUMPRODUCT(('Raw Data'!$D$2:$D$187=$A15)*('Raw Data'!$B$2:$B$187=(LEFT($B15,4)))*('Raw Data'!$C$2:$C$187=RIGHT($B15,2))*'Raw Data'!$G$2:$G$187)/C15} -> 0.39827554 | E15: =IF(AND(LEFT($B15,4)="2023",RIGHT($B15,2)="Q1"),"N/A",D15-D14) -> -0.0073077931 | F15: {=IF(LEFT($B15,4)="2023","N/A",D15-INDEX($D$8:$D$39,MATCH($A15&LEFT($B15,4)-1&RIGHT($B15,2),$A$8:$A$39&LEFT($B$8:$B$39,4)&RIGHT($B$8:$B$39,2),0)))} -> 0.010031228 | G15: =IF(D15>0.35,"Strong",IF(D15>=0.2,"Moderate","At Risk")) -> Strong
A16: Widget Standard | B16: 2023 Q1 | C16: =SUMIFS('Raw Data'!$E$2:$E$187,'Raw Data'!$D$2:$D$187,$A16,'Raw Data'!$B$2:$B$187,VALUE(LEFT($B16,4)),'Raw Data'!$C$2:$C$187,RIGHT($B16,2)) -> 71969 | D16: {=SUMPRODUCT(('Raw Data'!$D$2:$D$187=$A16)*('Raw Data'!$B$2:$B$187=(LEFT($B16,4)))*('Raw Data'!$C$2:$C$187=RIGHT($B16,2))*'Raw Data'!$G$2:$G$187)/C16} -> 0.26717364 | E16: =IF(AND(LEFT($B16,4)="2023",RIGHT($B16,2)="Q1"),"N/A",D16-D15) -> N/A | F16: {=IF(LEFT($B16,4)="2023","N/A",D16-INDEX($D$8:$D$39,MATCH($A16&LEFT($B16,4)-1&RIGHT($B16,2),$A$8:$A$39&LEFT($B$8:$B$39,4)&RIGHT($B$8:$B$39,2),0)))} -> N/A | G16: =IF(D16>0.35,"Strong",IF(D16>=0.2,"Moderate","At Risk")) -> Moderate
A17: Widget Standard | B17: 2023 Q2 | C17: =SUMIFS('Raw Data'!$E$2:$E$187,'Raw Data'!$D$2:$D$187,$A17,'Raw Data'!$B$2:$B$187,VALUE(LEFT($B17,4)),'Raw Data'!$C$2:$C$187,RIGHT($B17,2)) -> 88594 | D17: {=SUMPRODUCT(('Raw Data'!$D$2:$D$187=$A17)*('Raw Data'!$B$2:$B$187=(LEFT($B17,4)))*('Raw Data'!$C$2:$C$187=RIGHT($B17,2))*'Raw Data'!$G$2:$G$187)/C17} -> 0.26956882 | E17: =IF(AND(LEFT($B17,4)="2023",RIGHT($B17,2)="Q1"),"N/A",D17-D16) -> 0.0023951754 | F17: {=IF(LEFT($B17,4)="2023","N/A",D17-INDEX($D$8:$D$39,MATCH($A17&LEFT($B17,4)-1&RIGHT($B17,2),$A$8:$A$39&LEFT($B$8:$B$39,4)&RIGHT($B$8:$B$39,2),0)))} -> N/A | G17: =IF(D17>0.35,"Strong",IF(D17>=0.2,"Moderate","At Risk")) -> Moderate
A18: Widget Standard | B18: 2023 Q3 | C18: =SUMIFS('Raw Data'!$E$2:$E$187,'Raw Data'!$D$2:$D$187,$A18,'Raw Data'!$B$2:$B$187,VALUE(LEFT($B18,4)),'Raw Data'!$C$2:$C$187,RIGHT($B18,2)) -> 122105 | D18: {=SUMPRODUCT(('Raw Data'!$D$2:$D$187=$A18)*('Raw Data'!$B$2:$B$187=(LEFT($B18,4)))*('Raw Data'!$C$2:$C$187=RIGHT($B18,2))*'Raw Data'!$G$2:$G$187)/C18} -> 0.27581991 | E18: =IF(AND(LEFT($B18,4)="2023",RIGHT($B18,2)="Q1"),"N/A",D18-D17) -> 0.0062510895 | F18: {=IF(LEFT($B18,4)="2023","N/A",D18-INDEX($D$8:$D$39,MATCH($A18&LEFT($B18,4)-1&RIGHT($B18,2),$A$8:$A$39&LEFT($B$8:$B$39,4)&RIGHT($B$8:$B$39,2),0)))} -> N/A | G18: =IF(D18>0.35,"Strong",IF(D18>=0.2,"Moderate","At Risk")) -> Moderate
A19: Widget Standard | B19: 2023 Q4 | C19: =SUMIFS('Raw Data'!$E$2:$E$187,'Raw Data'!$D$2:$D$187,$A19,'Raw Data'!$B$2:$B$187,VALUE(LEFT($B19,4)),'Raw Data'!$C$2:$C$187,RIGHT($B19,2)) -> 151829 | D19: {=SUMPRODUCT(('Raw Data'!$D$2:$D$187=$A19)*('Raw Data'!$B$2:$B$187=(LEFT($B19,4)))*('Raw Data'!$C$2:$C$187=RIGHT($B19,2))*'Raw Data'!$G$2:$G$187)/C19} -> 0.2990567 | E19: =IF(AND(LEFT($B19,4)="2023",RIGHT($B19,2)="Q1"),"N/A",D19-D18) -> 0.023236793 | F19: {=IF(LEFT($B19,4)="2023","N/A",D19-INDEX($D$8:$D$39,MATCH($A19&LEFT($B19,4)-1&RIGHT($B19,2),$A$8:$A$39&LEFT($B$8:$B$39,4)&RIGHT($B$8:$B$39,2),0)))} -> N/A | G19: =IF(D19>0.35,"Strong",IF(D19>=0.2,"Moderate","At Risk")) -> Moderate
... A39: Accessory Kit | B39: 2024 Q4 | C39: =SUMIFS('Raw Data'!$E$2:$E$187,'Raw Data'!$D$2:$D$187,$A39,'Raw Data'!$B$2:$B$187,VALUE(LEFT($B39,4)),'Raw Data'!$C$2:$C$187,RIGHT($B39,2)) -> 35036 | D39: {=SUMPRODUCT(('Raw Data'!$D$2:$D$187=$A39)*('Raw Data'!$B$2:$B$187=(LEFT($B39,4)))*('Raw Data'!$C$2:$C$187=RIGHT($B39,2))*'Raw Data'!$G$2:$G$187)/C39} -> 0.18999657 | E39: =IF(AND(LEFT($B39,4)="2023",RIGHT($B39,2)="Q1"),"N/A",D39-D38) -> -0.026720866 | F39: {=IF(LEFT($B39,4)="2023","N/A",D39-INDEX($D$8:$D$39,MATCH($A39&LEFT($B39,4)-1&RIGHT($B39,2),$A$8:$A$39&LEFT($B$8:$B$39,4)&RIGHT($B$8:$B$39,2),0)))} -> -0.0033561789 | G39: =IF(D39>0.35,"Strong",IF(D39>=0.2,"Moderate","At Risk")) -> At Risk
A43: Chart Area
A44: Create clustered column chart with quarterly margins by product and secondary axis line for total revenue
